goodai/helpers/__init__.py
goodai/helpers/file_helper.py
goodai/helpers/html_helper.py
goodai/helpers/json_helper.py
goodai/helpers/sched_opt.py
goodai/helpers/tokenizer_helper.py
goodai/helpers/torch_helper.py
goodai/helpers/tests/test_json_helper.py
goodai/ltm/__init__.py
goodai/ltm/agent.py
goodai/ltm/version.py
goodai/ltm/data/__init__.py
goodai/ltm/data/cloud.py
goodai/ltm/data/names/__init__.py
goodai/ltm/data/names/wikidata-names.json
goodai/ltm/data/query_passage/__init__.py
goodai/ltm/data/query_passage/auto_data_source.py
goodai/ltm/data/query_passage/data_source.py
goodai/ltm/data/query_passage/dataset.py
goodai/ltm/data/query_passage/example.py
goodai/ltm/data/query_passage/qa.py
goodai/ltm/data/query_passage/qa_tok_entry.py
goodai/ltm/data/query_passage/sharc.py
goodai/ltm/data/query_passage/wiki.py
goodai/ltm/data/query_passage/wikianswers.py
goodai/ltm/data/query_passage/tests/__init__.py
goodai/ltm/data/query_passage/tests/test_query_passage_data_source.py
goodai/ltm/embeddings/__init__.py
goodai/ltm/embeddings/auto.py
goodai/ltm/embeddings/base.py
goodai/ltm/embeddings/contrast_classifier.py
goodai/ltm/embeddings/default.py
goodai/ltm/embeddings/emb_qp_prob_model.py
goodai/ltm/embeddings/flag_emb.py
goodai/ltm/embeddings/openai_emb.py
goodai/ltm/embeddings/st_emb.py
goodai/ltm/embeddings/trainable.py
goodai/ltm/eval/__init__.py
goodai/ltm/eval/auto.py
goodai/ltm/eval/mem.py
goodai/ltm/eval/metrics.py
goodai/ltm/eval/msmarco.py
goodai/ltm/eval/qp_ds.py
goodai/ltm/eval/qrecc.py
goodai/ltm/eval/strategy_qa.py
goodai/ltm/eval/tests/test_metrics.py
goodai/ltm/mem/__init__.py
goodai/ltm/mem/auto.py
goodai/ltm/mem/base.py
goodai/ltm/mem/chunk.py
goodai/ltm/mem/chunk_queue.py
goodai/ltm/mem/config.py
goodai/ltm/mem/default.py
goodai/ltm/mem/mem_foundation.py
goodai/ltm/mem/rewrite_model.py
goodai/ltm/mem/simple_vector_db.py
goodai/ltm/mem/tests/__init__.py
goodai/ltm/mem/tests/test_chunk_queue.py
goodai/ltm/mem/tests/test_chunk_queue_2.py
goodai_ltm-0.4.4.dist-info/LICENSE
goodai_ltm-0.4.4.dist-info/METADATA
goodai_ltm-0.4.4.dist-info/WHEEL
goodai_ltm-0.4.4.dist-info/top_level.txt
goodai_ltm-0.4.4.dist-info/RECORD
