Metadata-Version: 2.1
Name: goodai-ltm
Version: 0.4.4
Summary: A text memory meant to be used with conversational language models.
Home-page: https://github.com/GoodAI/goodai-ltm
License-File: LICENSE
Requires-Dist: torch (>=1.8.0)
Requires-Dist: pytest (>=7.0.0)
Requires-Dist: numpy (>=1.19.0)
Requires-Dist: transformers (>=4.34.0)
Requires-Dist: openai (>=1.0.0)
Requires-Dist: faiss-cpu
Requires-Dist: datasets
Requires-Dist: boto3
Requires-Dist: python-dotenv
Requires-Dist: sentence-transformers (>=2.2.2)
Requires-Dist: FlagEmbedding (>=1.1)
Requires-Dist: tiktoken (>=0.5.0)
Requires-Dist: litellm
Requires-Dist: cohere
